config/__init__.py
config/settings.py
database/__init__.py
database/base.py
database/postgres.py
entity/__init__.py
entity/billing_entity.py
entity/client_entity.py
entity/document_entity.py
entity/inventory_entity.py
entity/invoice_entity.py
entity/order_entity.py
entity/table_entity.py
entity/user_entity.py
models/__init__.py
models/billing_model.py
models/client_model.py
models/document_model.py
models/inventory_model.py
models/invoice_model.py
models/order_model.py
models/response_model.py
models/saas_context.py
models/table_model.py
models/user_model.py
utils/__init__.py
utils/auth.py
utils/category_builder.py
utils/create_notification.py
utils/send_email_otp.py
saas_common_lib_473815-0.6.dist-info/METADATA
saas_common_lib_473815-0.6.dist-info/WHEEL
saas_common_lib_473815-0.6.dist-info/top_level.txt
saas_common_lib_473815-0.6.dist-info/RECORD
