Metadata-Version: 2.4
Name: saas_common_lib_473815
Version: 0.6
Summary: Packaging all common functionalities
Home-page: 
Author: Srinidhi Nagarajan
Author-email: Srinidhinsn@gmail.com
License: BSD
Keywords: Saas application
Classifier: Development Status :: 3 - Alpha
Classifier: Intended Audience :: Developers
Classifier: License :: OSI Approved :: BSD License
Classifier: Operating System :: OS Independent
Classifier: Programming Language :: Python :: 3
Dynamic: author
Dynamic: author-email
Dynamic: classifier
Dynamic: keywords
Dynamic: license
Dynamic: summary
